collibra_search/__init__.py
collibra_search/api_client.py
collibra_search/configuration.py
collibra_search/rest.py
collibra_search/api/__init__.py
collibra_search/api/search_api.py
collibra_search/models/__init__.py
collibra_search/models/find_search_views_request.py
collibra_search/models/paged_response_search_view.py
collibra_search/models/search_aggregation.py
collibra_search/models/search_asset_result_resource.py
collibra_search/models/search_community_result_resource.py
collibra_search/models/search_domain_result_resource.py
collibra_search/models/search_filter.py
collibra_search/models/search_highlight.py
collibra_search/models/search_in_fields.py
collibra_search/models/search_request.py
collibra_search/models/search_response.py
collibra_search/models/search_response_aggregation.py
collibra_search/models/search_response_aggregation_value.py
collibra_search/models/search_result.py
collibra_search/models/search_result_highlight.py
collibra_search/models/search_result_resource.py
collibra_search/models/search_result_status.py
collibra_search/models/search_result_type.py
collibra_search/models/search_user_group_result_resource.py
collibra_search/models/search_user_result_resource.py
collibra_search/models/search_view.py
collibra_search/models/search_view_paged_response.py
test/__init__.py
test/test_find_search_views_request.py
test/test_paged_response_search_view.py
test/test_search_aggregation.py
test/test_search_api.py
test/test_search_asset_result_resource.py
test/test_search_community_result_resource.py
test/test_search_domain_result_resource.py
test/test_search_filter.py
test/test_search_highlight.py
test/test_search_in_fields.py
test/test_search_request.py
test/test_search_response.py
test/test_search_response_aggregation.py
test/test_search_response_aggregation_value.py
test/test_search_result.py
test/test_search_result_highlight.py
test/test_search_result_resource.py
test/test_search_result_status.py
test/test_search_result_type.py
collibra_search_200-2.0.0.dist-info/METADATA
collibra_search_200-2.0.0.dist-info/WHEEL
collibra_search_200-2.0.0.dist-info/top_level.txt
collibra_search_200-2.0.0.dist-info/RECORD
