Metadata-Version: 2.1
Name: collibra-search-200
Version: 2.0.0
Summary: Collibra Search API
Home-page: 
Author-email: 
Keywords: Swagger,Collibra Search API
Requires-Dist: urllib3 (>=1.15)
Requires-Dist: six (>=1.10)
Requires-Dist: certifi
Requires-Dist: python-dateutil
